beecloud/__init__.py
beecloud/entity.py
beecloud/pay.py
beecloud/query.py
beecloud/sales.py
beecloud/subscribe.py
beecloud/user.py
beecloud/utils.py
beecloud-3.6.0.dist-info/DESCRIPTION.rst
beecloud-3.6.0.dist-info/METADATA
beecloud-3.6.0.dist-info/RECORD
beecloud-3.6.0.dist-info/WHEEL
beecloud-3.6.0.dist-info/metadata.json
beecloud-3.6.0.dist-info/top_level.txt
