Metadata-Version: 2.0
Name: beecloud
Version: 3.6.0
Summary: beecloud, make payment simpler
Home-page: https://beecloud.cn/
Author: xuanzhui
Author-email: david@beecloud.cn
License: MIT License
Keywords: beecloud,pay
Platform: 2.7
Platform: 3.4
Platform: 3.5
Platform: 3.6
Classifier: Intended Audience :: Developers
Classifier: License :: OSI Approved :: MIT License
Classifier: Operating System :: OS Independent
Classifier: Programming Language :: Python
Classifier: Programming Language :: Python :: 2
Classifier: Programming Language :: Python :: 2.7
Classifier: Programming Language :: Python :: 3
Classifier: Programming Language :: Python :: 3.4
Classifier: Programming Language :: Python :: 3.5
Classifier: Programming Language :: Python :: 3.6
Classifier: Topic :: Software Development :: Libraries :: Python Modules
Requires-Dist: requests
